{
    "entryPoints": [
        "src/index.ts",
        "src/interfaces/CommentType.ts",
        "src/interfaces/EngineOutput.ts",
        "src/interfaces/index.ts",
        "src/interfaces/sizeFormat.ts",
        "src/interfaces/TubeResponse.ts",
        "src/routes/Account/History.ts",
        "src/routes/Account/HomeFeed.ts",
        "src/routes/Account/SubscriptionsFeed.ts",
        "src/routes/Account/UnseenNotifications.ts",
        "src/routes/Audio/Custom.ts",
        "src/routes/Audio/Highest.ts",
        "src/routes/Audio/Lowest.ts",
        "src/routes/Audio_Video/Custom.ts",
        "src/routes/Audio_Video/Highest.ts",
        "src/routes/Audio_Video/Lowest.ts",
        "src/routes/Misc/System/Help.ts",
        "src/routes/Misc/Video/Comments.ts",
        "src/routes/Misc/Video/Extract.ts",
        "src/routes/Misc/Video/Related.ts",
        "src/routes/Misc/Video/Transcript.ts",
        "src/routes/Search/Channel/Multiple.ts",
        "src/routes/Search/Channel/Single.ts",
        "src/routes/Search/Playlist/Multiple.ts",
        "src/routes/Search/Playlist/Single.ts",
        "src/routes/Search/Video/Multiple.ts",
        "src/routes/Search/Video/Single.ts",
        "src/routes/Video/Custom.ts",
        "src/routes/Video/Highest.ts",
        "src/routes/Video/Lowest.ts",
        "src/utils/Agent.ts",
        "src/utils/Engine.ts",
        "src/utils/ExtractText.ts",
        "src/utils/Locator.ts",
        "src/utils/M3u8.ts",
        "src/utils/ProgBar.ts",
        "src/utils/SanitizeContentItem.ts",
        "src/utils/SanitizeRenderer.ts",
        "src/utils/TubeLogin.ts",
        "src/utils/YouTubeId.ts"
    ],
    "out": "docs",
    "excludePrivate": true,
    "excludeProtected": true,
    "excludeInternal": true,
    "readme": "README.md",
    "githubPages": true,
    "excludeExternals": true,
    "exclude": ["src/cli/**/*.ts", "src/spec/**/*.ts"],
    "entryPointStrategy": "expand"
}
